selenium_seo/__init__.py
selenium_seo/selenium_seo.py
selenium_seo-1.0.0.dist-info/LICENSE
selenium_seo-1.0.0.dist-info/METADATA
selenium_seo-1.0.0.dist-info/WHEEL
selenium_seo-1.0.0.dist-info/top_level.txt
selenium_seo-1.0.0.dist-info/RECORD
