Metadata-Version: 2.1
Name: selenium-seo
Version: 1.0.0
Summary: selenium-seo extends Selenium by providing a keyword analyzer on a given webpage
Home-page: https://github.com/shbenzer/selenium-seo
Author: Simon Benzer
Author-email: SimonHBenzer@gmail.com
Classifier: Programming Language :: Python :: 3
Classifier: License :: OSI Approved :: Apache Software License
Classifier: Operating System :: OS Independent
Requires-Python: >=3.7
License-File: LICENSE
Requires-Dist: selenium>=4.0.0
Requires-Dist: beautifulsoup4>=4.10.0
